parseit/__init__.py
parseit/parseit.py
parseit/treeify.py
parseit-1.0.1.dist-info/DESCRIPTION.rst
parseit-1.0.1.dist-info/METADATA
parseit-1.0.1.dist-info/RECORD
parseit-1.0.1.dist-info/WHEEL
parseit-1.0.1.dist-info/metadata.json
parseit-1.0.1.dist-info/top_level.txt
